rfskiosk2/__init__.py
rfskiosk2/envfiles/base-example.env
rfskiosk2/envfiles/local-example.env
rfskiosk2/envfiles/nfcreader-example.ini
rfskiosk2/kiosk_beeper.py
rfskiosk2/nfcreader3.py
rfskiosk2-0.4.21.dist-info/METADATA
rfskiosk2-0.4.21.dist-info/WHEEL
rfskiosk2-0.4.21.dist-info/entry_points.txt
rfskiosk2-0.4.21.dist-info/RECORD
